yInference/__init__.py
yInference/infer.py
yInference-0.0.1.2.dist-info/LICENSE
yInference-0.0.1.2.dist-info/METADATA
yInference-0.0.1.2.dist-info/WHEEL
yInference-0.0.1.2.dist-info/top_level.txt
yInference-0.0.1.2.dist-info/RECORD
