Metadata-Version: 2.1
Name: yInference
Version: 0.0.1.2
Summary: Inference your Fine tuned LLM
Author: Shuvam Mandal
Author-email: shuvammandal121@gmail.com
License-File: LICENSE
Requires-Dist: transformers
Requires-Dist: pandas
Requires-Dist: tensorflow
